d1_test/__init__.py
d1_test/d1_test_case.py
d1_test/pycharm.py
d1_test/sample.py
d1_test/slender_node_test_client.py
d1_test/test_files.py
d1_test/xml_normalize.py
d1_test/instance_generator/__init__.py
d1_test/instance_generator/access_policy.py
d1_test/instance_generator/checksum.py
d1_test/instance_generator/date_time.py
d1_test/instance_generator/format_id.py
d1_test/instance_generator/identifier.py
d1_test/instance_generator/media_type.py
d1_test/instance_generator/names.py
d1_test/instance_generator/node_ref.py
d1_test/instance_generator/person.py
d1_test/instance_generator/random_data.py
d1_test/instance_generator/replica.py
d1_test/instance_generator/replication_policy.py
d1_test/instance_generator/replication_status.py
d1_test/instance_generator/sciobj.py
d1_test/instance_generator/subject.py
d1_test/instance_generator/system_metadata.py
d1_test/instance_generator/unicode_names.py
d1_test/instance_generator/unicode_test_strings.py
d1_test/instance_generator/user_agent.py
d1_test/instance_generator/words.py
d1_test/instance_generator/tests/__init__.py
d1_test/instance_generator/tests/test_access_policy.py
d1_test/instance_generator/tests/test_checksum.py
d1_test/instance_generator/tests/test_datetime.py
d1_test/instance_generator/tests/test_format_id.py
d1_test/instance_generator/tests/test_identifier.py
d1_test/instance_generator/tests/test_person.py
d1_test/instance_generator/tests/test_random_data.py
d1_test/instance_generator/tests/test_replica.py
d1_test/instance_generator/tests/test_replication_policy.py
d1_test/instance_generator/tests/test_sciobj.py
d1_test/instance_generator/tests/test_subject.py
d1_test/instance_generator/tests/test_systemmetadata.py
d1_test/instance_generator/tests/test_user_agent.py
d1_test/mock_api/__init__.py
d1_test/mock_api/catch_all.py
d1_test/mock_api/create.py
d1_test/mock_api/d1_exception.py
d1_test/mock_api/describe.py
d1_test/mock_api/django_client.py
d1_test/mock_api/echo_credentials.py
dataone.test_utilities-3.5.2.dist-info/METADATA
dataone.test_utilities-3.5.2.dist-info/WHEEL
dataone.test_utilities-3.5.2.dist-info/top_level.txt
dataone.test_utilities-3.5.2.dist-info/RECORD
